Metadata-Version: 2.1
Name: xwakes
Version: 0.2.7
Summary: Wake and impedance toolbox
Home-page: https://xsuite.web.cern.ch/
Download-URL: https://pypi.python.org/pypi/xwakes
Author: M. Rognlien, L. Giacomel, D. Amorim, E. Vik, G. Iadarola and N. Mounet
License: Apache 2.0
Project-URL: Bug Tracker, https://github.com/xsuite/xwakes/issues
Project-URL: Source Code, https://github.com/xsuite/xwakes/
Provides-Extra: tests
License-File: LICENSE
